MANIFEST.in
README.txt
setup.py
cvtgear/__init__.py
cvtgear/module1.py
cvtgear/olafile.ipynb
cvtgear.egg-info/PKG-INFO
cvtgear.egg-info/SOURCES.txt
cvtgear.egg-info/dependency_links.txt
cvtgear.egg-info/top_level.txt