Metadata-Version: 2.1
Name: cvtgear
Version: 0.0.1
Summary: aa
Home-page: 
Author: Joshua
Author-email: abc@edub.org
License: MIT
Keywords: calculator
Classifier: Development Status :: 5 - Production/Stable
Classifier: Intended Audience :: Education
Classifier: Operating System :: Microsoft :: Windows :: Windows 10
Classifier: License :: OSI Approved :: MIT License
Classifier: Programming Language :: Python :: 3
